{
  "_class": "group",
  "do_objectID": "02C47C10-7D54-473E-9954-97741586C0AB",
  "exportOptions": {
    "_class": "exportOptions",
    "exportFormats": [
    ],
    "includedLayerIds": [
    ],
    "layerOptions": 0,
    "shouldTrim": false
  },
  "frame": {
    "_class": "rect",
    "constrainProportions": false,
    "height": 510,
    "width": 742,
    "x": 433,
    "y": 3552
  },
  "hasClickThrough": false,
  "isFlippedHorizontal": false,
  "isFlippedVertical": false,
  "isLocked": false,
  "isVisible": true,
  "layerListExpandedType": 0,
  "layers": [
    {
      "class": "bitmap",
      "id": "B0AD7EA5-342C-4EFE-A4C1-34F58B248061"
    },
    {
      "class": "group",
      "id": "4C42A046-808C-4505-B70F-1E66CC11ADB4"
    },
    {
      "class": "group",
      "id": "3FE00672-6D44-4C51-B367-76F1CAC035D2"
    }
  ],
  "name": "09 copy 3",
  "nameIsFixed": true,
  "resizingConstraint": 63,
  "resizingType": 0,
  "rotation": 0,
  "shouldBreakMaskChain": false,
  "style": {
    "_class": "style",
    "blur": {
      "_class": "blur",
      "center": "{0.5, 0.5}",
      "isEnabled": false,
      "motionAngle": 0,
      "radius": 2.5,
      "type": 0
    },
    "endDecorationType": 0,
    "miterLimit": 10,
    "startDecorationType": 0
  }
}