{
  "_class": "group",
  "do_objectID": "E9A04CA6-C3F2-49C2-A83A-590BB2B159CD",
  "exportOptions": {
    "_class": "exportOptions",
    "exportFormats": [
    ],
    "includedLayerIds": [
    ],
    "layerOptions": 0,
    "shouldTrim": false
  },
  "frame": {
    "_class": "rect",
    "constrainProportions": false,
    "height": 4.545454545454545,
    "width": 16.36363636363636,
    "x": 28.63636363636364,
    "y": 26.39136363636364
  },
  "hasClickThrough": false,
  "isFlippedHorizontal": false,
  "isFlippedVertical": false,
  "isLocked": false,
  "isVisible": true,
  "layerListExpandedType": 0,
  "layers": [
    {
      "class": "shapeGroup",
      "id": "9A5C8A27-D222-4B46-89E2-FE6FC4EE3ADA"
    },
    {
      "class": "shapeGroup",
      "id": "9078EA47-0943-497A-A35A-A1C06FA0261C"
    }
  ],
  "name": "Group 60",
  "nameIsFixed": false,
  "resizingConstraint": 63,
  "resizingType": 0,
  "rotation": 0,
  "shouldBreakMaskChain": false,
  "style": {
    "_class": "style",
    "blur": {
      "_class": "blur",
      "center": "{0.5, 0.5}",
      "isEnabled": false,
      "motionAngle": 0,
      "radius": 4.545454545454545,
      "type": 0
    },
    "endDecorationType": 0,
    "miterLimit": 10,
    "startDecorationType": 0
  }
}