{
  "_class": "shapeGroup",
  "clippingMaskMode": 0,
  "do_objectID": "502E6105-760E-49BC-865F-87D7F6A5C20C",
  "exportOptions": {
    "_class": "exportOptions",
    "exportFormats": [
    ],
    "includedLayerIds": [
    ],
    "layerOptions": 0,
    "shouldTrim": false
  },
  "frame": {
    "_class": "rect",
    "constrainProportions": false,
    "height": 2.054205607476636,
    "width": 7.553292929292936,
    "x": 101.7131555555556,
    "y": 143.5992523364486
  },
  "hasClickThrough": false,
  "hasClippingMask": false,
  "isFlippedHorizontal": false,
  "isFlippedVertical": false,
  "isLocked": false,
  "isVisible": true,
  "layerListExpandedType": 0,
  "layers": [
    {
      "class": "shapePath",
      "id": "E42F0BB8-75CA-4584-9B8A-BCD26A654F9C"
    }
  ],
  "name": "Fill 62",
  "nameIsFixed": false,
  "resizingConstraint": 63,
  "resizingType": 0,
  "rotation": 0,
  "shouldBreakMaskChain": false,
  "style": {
    "_class": "style",
    "blur": {
      "_class": "blur",
      "center": "{0.5, 0.5}",
      "isEnabled": false,
      "motionAngle": 0,
      "radius": 18.69158878504673,
      "type": 0
    },
    "endDecorationType": 0,
    "fills": [
      {
        "_class": "fill",
        "color": {
          "_class": "color",
          "alpha": 1,
          "blue": 0.125,
          "green": 0.278,
          "red": 0.659
        },
        "fillType": 0,
        "isEnabled": true,
        "noiseIndex": 0,
        "noiseIntensity": 0,
        "patternFillType": 1,
        "patternTileScale": 1
      }
    ],
    "miterLimit": 10,
    "startDecorationType": 0
  },
  "windingRule": 1
}