{
  "_class": "group",
  "do_objectID": "DA285FA0-648E-43E6-A198-246CC3B99A07",
  "exportOptions": {
    "_class": "exportOptions",
    "exportFormats": [
    ],
    "includedLayerIds": [
    ],
    "layerOptions": 0,
    "shouldTrim": false
  },
  "frame": {
    "_class": "rect",
    "constrainProportions": false,
    "height": 90,
    "width": 100,
    "x": 270,
    "y": 78
  },
  "hasClickThrough": false,
  "isFlippedHorizontal": false,
  "isFlippedVertical": false,
  "isLocked": false,
  "isVisible": true,
  "layerListExpandedType": 0,
  "layers": [
    {
      "class": "shapeGroup",
      "id": "7C19843B-6379-417F-A3FA-62520F1B3981"
    },
    {
      "class": "shapeGroup",
      "id": "7212EA81-E231-4758-AA7F-EACD0D92B0FA"
    }
  ],
  "name": "错",
  "nameIsFixed": false,
  "resizingConstraint": 63,
  "resizingType": 0,
  "rotation": 0,
  "shouldBreakMaskChain": false,
  "style": {
    "_class": "style",
    "blur": {
      "_class": "blur",
      "center": "{0.5, 0.5}",
      "isEnabled": false,
      "motionAngle": 0,
      "radius": 1.265822784810127,
      "type": 0
    },
    "endDecorationType": 0,
    "miterLimit": 10,
    "startDecorationType": 0
  }
}