{
  "_class": "group",
  "do_objectID": "1C6919AD-0E33-43B6-A35A-9E51D9776586",
  "exportOptions": {
    "_class": "exportOptions",
    "exportFormats": [
    ],
    "includedLayerIds": [
    ],
    "layerOptions": 0,
    "shouldTrim": false
  },
  "frame": {
    "_class": "rect",
    "constrainProportions": false,
    "height": 43,
    "width": 400,
    "x": 0,
    "y": 0
  },
  "hasClickThrough": false,
  "isFlippedHorizontal": false,
  "isFlippedVertical": false,
  "isLocked": false,
  "isVisible": true,
  "layerListExpandedType": 0,
  "layers": [
    {
      "class": "shapeGroup",
      "id": "55BDE43A-3A5B-49D4-B898-EC1EC505EB54"
    },
    {
      "class": "symbolInstance",
      "id": "B7F3F5A2-B9A1-4C21-B4E1-8812F0914767"
    },
    {
      "class": "text",
      "id": "6F25C94F-06E3-4696-A04F-FD52233FEDC3"
    }
  ],
  "name": "Group 3",
  "nameIsFixed": false,
  "resizingConstraint": 63,
  "resizingType": 0,
  "rotation": 0,
  "shouldBreakMaskChain": false,
  "style": {
    "_class": "style",
    "endDecorationType": 0,
    "miterLimit": 10,
    "startDecorationType": 0
  }
}